{"sceneObjects":[{"position":{"width":46.21478873239437,"top":334.1538461538462,"height":49.84615384615385,"left":166.3732394366197},"id":0,"inText":true,"label":"model fire engine"}],"triggers":[{"args":{"textId":5,"timestamp":null,"sceneObjectId":0},"type":0},{"args":{"textId":6,"timestamp":null,"sceneObjectId":0},"type":0},{"args":{"textId":7,"timestamp":null,"sceneObjectId":0},"type":0}], "text": "Gertie's present was a tiny model fire engine with a siren that really worked, and Henry loved it.", "storyImageFile": "henrys_happy_birthday_27", "audioFile": "henrys_happy_birthday_26", "timestamps": [{"start": "0.0", "wordIdx": "0", "end": "0.4"}, {"start": "0.4", "wordIdx": "1", "end": "0.7"}, {"start": "0.7", "wordIdx": "2", "end": "1.4"}, {"start": "1.4", "wordIdx": "3", "end": "1.5"}, {"start": "1.5", "wordIdx": "4", "end": "1.9"}, {"start": "1.9", "wordIdx": "5", "end": "2.6"}, {"start": "2.6", "wordIdx": "6", "end": "3.0"}, {"start": "3.0", "wordIdx": "7", "end": "3.6"}, {"start": "3.6", "wordIdx": "8", "end": "4.2"}, {"start": "4.2", "wordIdx": "9", "end": "4.3"}, {"start": "4.3", "wordIdx": "10", "end": "4.8"}, {"start": "4.8", "wordIdx": "11", "end": "5.1"}, {"start": "5.1", "wordIdx": "12", "end": "5.4"}, {"start": "5.4", "wordIdx": "13", "end": "6.1"}, {"start": "6.1", "wordIdx": "14", "end": "6.7"}, {"start": "6.7", "wordIdx": "15", "end": "7.2"}, {"start": "7.2", "wordIdx": "16", "end": "7.425"}, {"start": "7.425", "wordIdx": "17", "end": "7.5"}], "isTitle": false}