{"sceneObjects": [{"position": {"width": 224, "top": 153, "height": 267, "left": 76}, "id": 0, "inText": true, "label": "jumped"}, {"position": {"width": 146, "top": 370, "height": 25, "left": 124}, "id": 1, "inText": true, "label": "slippers"}, {"position": {"width": 46, "top": 94, "height": 83, "left": 224}, "id": 2, "inText": false, "label": "ribbon"}, {"position": {"width": 118, "top": 378, "height": 21, "left": 135}, "id": 3, "inText": true, "label": "slippers"}, {"position": {"width": 31, "top": 248, "height": 65, "left": 164}, "id": 4, "inText": true, "label": "henry"}, {"position": {"width": 165, "top": 306, "height": 40, "left": 286}, "id": 5, "inText": true, "label": "bed"}, {"position": {"width": 59, "top": 280, "height": 19, "left": 148}, "id": 6, "inText": true, "label": "henry"}, {"position": {"width": 27, "top": 376, "height": 17, "left": 215}, "id": 7, "inText": true, "label": "slippers"}, {"position": {"width": 72, "top": 94, "height": 29, "left": 181}, "id": 8, "inText": false, "label": "award"}], "triggers": [{"args": {"textId": 1, "timestamp": null, "sceneObjectId": 0}, "type": 0}, {"args": {"textId": 8, "timestamp": null, "sceneObjectId": 1}, "type": 0}, {"args": {"textId": 8, "timestamp": null, "sceneObjectId": 3}, "type": 0}, {"args": {"textId": 0, "timestamp": null, "sceneObjectId": 4}, "type": 0}, {"args": {"textId": 4, "timestamp": null, "sceneObjectId": 5}, "type": 0}, {"args": {"textId": 0, "timestamp": null, "sceneObjectId": 6}, "type": 0}, {"args": {"textId": 8, "timestamp": null, "sceneObjectId": 7}, "type": 0}], "text": "Henry jumped out of bed and  donned  his slippers. He cleared this throat and started to sing. \"Happy birthday to me, happy birthday to me...\"", "storyImageFile": "henrys_happy_birthday_03", "audioFile": "henrys_happy_birthday_2", "timestamps": [{"start": "0.0", "wordIdx": "0", "end": "0.3"}, {"start": "0.3", "wordIdx": "1", "end": "0.8"}, {"start": "0.8", "wordIdx": "2", "end": "0.8"}, {"start": "0.8", "wordIdx": "3", "end": "1.0"}, {"start": "1.0", "wordIdx": "4", "end": "1.1"}, {"start": "1.1", "wordIdx": "5", "end": "1.6"}, {"start": "1.6", "wordIdx": "6", "end": "2.0"}, {"start": "2.0", "wordIdx": "7", "end": "2.6"}, {"start": "2.6", "wordIdx": "8", "end": "3.2"}, {"start": "3.2", "wordIdx": "9", "end": "3.9"}, {"start": "3.9", "wordIdx": "10", "end": "4.4"}, {"start": "4.4", "wordIdx": "11", "end": "4.5"}, {"start": "4.5", "wordIdx": "12", "end": "4.7"}, {"start": "4.7", "wordIdx": "13", "end": "5.2"}, {"start": "5.2", "wordIdx": "14", "end": "5.7"}, {"start": "5.7", "wordIdx": "15", "end": "5.9"}, {"start": "5.9", "wordIdx": "16", "end": "6.2"}, {"start": "6.2", "wordIdx": "17", "end": "7.0"}, {"start": "7.0", "wordIdx": "18", "end": "7.2"}, {"start": "7.2", "wordIdx": "19", "end": "8.1"}, {"start": "8.1", "wordIdx": "20", "end": "8.8"}, {"start": "8.8", "wordIdx": "21", "end": "9.7"}, {"start": "9.7", "wordIdx": "22", "end": "10.1"}, {"start": "10.1", "wordIdx": "23", "end": "10.9"}, {"start": "10.9", "wordIdx": "24", "end": "11.6"}], "isTitle": false}