{"sceneObjects": [], "triggers": [], "text": "Jim Jot has a job. He will fly the jet.", "storyImageFile": "clifford_and_the_jet_02", "audioFile": "clifford_and_the_jet_1", "timestamps": [{"start": "0.0", "wordIdx": "0", "end": "0.9"}, {"start": "0.9", "wordIdx": "1", "end": "1.3875"}, {"start": "1.3875", "wordIdx": "2", "end": "1.7"}, {"start": "1.7", "wordIdx": "3", "end": "1.8"}, {"start": "1.8", "wordIdx": "4", "end": "2.2"}, {"start": "2.2", "wordIdx": "5", "end": "3.0"}, {"start": "3.0", "wordIdx": "6", "end": "3.3"}, {"start": "3.3", "wordIdx": "7", "end": "3.7"}, {"start": "3.7", "wordIdx": "8", "end": "4.0"}, {"start": "4.0", "wordIdx": "9", "end": "4.69580498866"}], "isTitle": false}